quasargui/__init__.py
quasargui/base.py
quasargui/callbacks.py
quasargui/components.py
quasargui/layout.py
quasargui/main.py
quasargui/model.py
quasargui/plot.py
quasargui/quasar_components.py
quasargui/quasar_form.py
quasargui/quasar_form_improved.py
quasargui/quasar_plugins.py
quasargui/tools.py
quasargui/typing.py
quasargui/vue_tags_input.py
quasargui/assets/d3.v5.js
quasargui/assets/index.html
quasargui/assets/lodash.min.js
quasargui/assets/material-icons.css
quasargui/assets/material-icons.woff2
quasargui/assets/mpld3-figure.js
quasargui/assets/mpld3.v0.5.2.js
quasargui/assets/quasar.min.css
quasargui/assets/quasar.umd.min.js
quasargui/assets/quasar_plugins.js
quasargui/assets/script.js
quasargui/assets/styles.css
quasargui/assets/vue-tags-input.2.1.0.js
quasargui/assets/vue-tags-input.css
quasargui/assets/vue-tags-input.js.map
quasargui/assets/vue.min.js
quasargui-0.1.1.dist-info/AUTHORS
quasargui-0.1.1.dist-info/LICENSE
quasargui-0.1.1.dist-info/METADATA
quasargui-0.1.1.dist-info/WHEEL
quasargui-0.1.1.dist-info/top_level.txt
quasargui-0.1.1.dist-info/RECORD
