Metadata-Version: 2.1
Name: quasargui
Version: 0.1.1
Summary: Drop-in replacement GUI for Django testing.
Home-page: https://github.com/BarnabasSzabolcs/pyquasargui
Author: Barney Szabolcs
Author-email: szabolcs.barnabas@gmail.com
License: UNKNOWN
Keywords: Python GUI,python gui,python,GUI
Platform: UNKNOWN
Classifier: Intended Audience :: Developers
Classifier: Operating System :: OS Independent
Classifier: Programming Language :: Python
Classifier: Programming Language :: Python :: 3
Classifier: License :: OSI Approved :: MIT License
Requires-Python: >=3.6
License-File: LICENSE
License-File: AUTHORS
Requires-Dist: pywebview (>=3.5)
Requires-Dist: cefpython3 (>=66.0)
